{
  "compileType": "miniprogram",
  "libVersion": "trial",
  "packOptions": {
    "ignore": [],
    "include": []
  },
  "setting": {
    "coverView": true,
    "es6": true,
    "postcss": true,
    "minified": true,
    "enhance": true,
    "showShadowRootInWxmlPanel": true,
    "packNpmRelationList": [],
    "babelSetting": {
      "ignore": [],
      "disablePlugins": [],
      "outputPath": ""
    },
    "ignoreUploadUnusedFiles": true,
    "uglifyFileName": true,
    "condition": true,
    "compileWorklet": true
  },
  "condition": {},
  "editorSetting": {
    "tabIndent": "auto",
    "tabSize": 2
  },
  "appid": "wxaf77f0b578920b6d",
  "projectArchitecture": "multiPlatform",
  "simulatorPluginLibVersion": {
    "wxext14566970e7e9f62": "3.0.2-8"
  }
}